mcxlib/__init__.py
mcxlib/libutil.py
mcxlib/logger.py
mcxlib/market_data.py
mcxlib-0.1.dist-info/LICENSE
mcxlib-0.1.dist-info/METADATA
mcxlib-0.1.dist-info/WHEEL
mcxlib-0.1.dist-info/top_level.txt
mcxlib-0.1.dist-info/RECORD
