Metadata-Version: 2.1
Name: mcxlib
Version: 0.1
Summary: python library to get MCX India data
Home-page: https://github.com/RuchiTanmay/mcxlib
Author: RuchiTanmay
Author-email: ruchitanmay@gmail.com
Keywords: mcx,mcx india,python,mcx data,mcx history data,commodity,mcx python,mcx python library,mcx library
Classifier: Intended Audience :: Developers
Classifier: Natural Language :: English
Classifier: Operating System :: OS Independent
Classifier: Programming Language :: Python
Classifier: Programming Language :: Python :: 3
Classifier: Programming Language :: Python :: Implementation :: PyPy
Classifier: Topic :: Software Development :: Libraries :: Python Modules
License-File: LICENSE
Requires-Dist: requests
Requires-Dist: pandas
